manageconf/__init__.py
manageconf/exceptions.py
manageconf-1.1.1.dist-info/LICENSE
manageconf-1.1.1.dist-info/WHEEL
manageconf-1.1.1.dist-info/METADATA
manageconf-1.1.1.dist-info/RECORD
